<?xml version="1.0" encoding="utf-8"?>
<!DOCTYPE hibernate-mapping PUBLIC "-//Hibernate/Hibernate Mapping DTD 3.0//EN"
"http://hibernate.sourceforge.net/hibernate-mapping-3.0.dtd">
<!-- 
    Mapping file autogenerated by MyEclipse Persistence Tools
-->
<hibernate-mapping>
    <class name="com.combanc.itsm.pojo.TaskDep" table="task_dep" catalog="itsm">
        <composite-id name="id" class="com.combanc.itsm.pojo.TaskDepId">
            <key-property name="departmentId" type="java.lang.Integer">
                <column name="departmentID" />
            </key-property>
            <key-property name="taskId" type="java.lang.Integer">
                <column name="taskID" />
            </key-property>
        </composite-id>
        <many-to-one name="taskallocation" class="com.combanc.itsm.pojo.TaskAllocation" update="false" insert="false" fetch="select">
            <column name="taskID" not-null="true" />
        </many-to-one>
        <many-to-one name="department" class="com.combanc.itsm.pojo.Department" update="false" insert="false" fetch="select">
            <column name="departmentID" not-null="true" />
        </many-to-one>
         <property name="taskId" type="java.lang.Integer" insert="false" update="false">
			<column name="taskID">
			</column>
		</property>
		 <property name="departmentId" type="java.lang.Integer" insert="false" update="false">
			<column name="departmentID">
			</column>
		</property>
    </class>
</hibernate-mapping>
